rogue_tools/__init__.py
rogue_tools/android_tool.py
rogue_tools/excel_tool.py
rogue_tools/file_tool.py
rogue_tools/filter_tool.py
rogue_tools/ini_tool.py
rogue_tools/install_tools.py
rogue_tools/json_tool.py
rogue_tools/new_excel_tool.py
rogue_tools/path_tool.py
rogue_tools/robot_tool.py
rogue_tools/show_tool.py
rogue_tools/signal.py
rogue_tools/string_tool.py
rogue_tools/thread_tool.py
rogue_tools/time_tool.py
rogue_tools/ui_tool.py
rogue_tools/web_tool.py
rogue_tools/win_tool.py
rogue_tools/yaml_tool.py
rogue_tools/zip_tool.py
rogue_tools-1.1.29.dist-info/METADATA
rogue_tools-1.1.29.dist-info/WHEEL
rogue_tools-1.1.29.dist-info/top_level.txt
rogue_tools-1.1.29.dist-info/zip-safe
rogue_tools-1.1.29.dist-info/RECORD
