Metadata-Version: 2.1
Name: rogue-tools
Version: 1.1.29
Summary: private tools
Home-page: 
Author: luohao
Author-email: luohao@aobi.com
License: MIT
Classifier: Operating System :: Microsoft
Classifier: Intended Audience :: Developers
Classifier: License :: OSI Approved :: MIT License
Classifier: Programming Language :: Python
Classifier: Programming Language :: Python :: 3
Classifier: Programming Language :: Python :: 3.10
Classifier: Topic :: Software Development :: Libraries
Requires-Dist: openpyxl (>=3.0.10)
Requires-Dist: requests (>=2.28.1)
Requires-Dist: matplotlib (>=3.7.0)
Requires-Dist: tqdm (>=4.64.1)
Requires-Dist: PyYaml (>=5.3)
Requires-Dist: lz4 (>=4.3.2)
Requires-Dist: deepdiff (>=7.0.1)
